hbase/__init__.py
hbase/conf.py
hbase/connection.py
hbase/exceptions.py
hbase/namespace.py
hbase/shell.py
hbase/stream_io.py
hbase/table.py
hbase/client/__init__.py
hbase/client/bstree.py
hbase/client/client.py
hbase/client/filters.py
hbase/client/rbtree.py
hbase/client/region.py
hbase/protobuf/AccessControl_pb2.py
hbase/protobuf/Admin_pb2.py
hbase/protobuf/Aggregate_pb2.py
hbase/protobuf/Authentication_pb2.py
hbase/protobuf/Cell_pb2.py
hbase/protobuf/Client_pb2.py
hbase/protobuf/ClusterId_pb2.py
hbase/protobuf/ClusterStatus_pb2.py
hbase/protobuf/Comparator_pb2.py
hbase/protobuf/Encryption_pb2.py
hbase/protobuf/ErrorHandling_pb2.py
hbase/protobuf/FS_pb2.py
hbase/protobuf/Filter_pb2.py
hbase/protobuf/HBase_pb2.py
hbase/protobuf/HFile_pb2.py
hbase/protobuf/LoadBalancer_pb2.py
hbase/protobuf/MapReduce_pb2.py
hbase/protobuf/MasterProcedure_pb2.py
hbase/protobuf/Master_pb2.py
hbase/protobuf/MultiRowMutation_pb2.py
hbase/protobuf/Procedure_pb2.py
hbase/protobuf/Quota_pb2.py
hbase/protobuf/RPC_pb2.py
hbase/protobuf/RegionNormalizer_pb2.py
hbase/protobuf/RegionServerStatus_pb2.py
hbase/protobuf/RowProcessor_pb2.py
hbase/protobuf/SecureBulkLoad_pb2.py
hbase/protobuf/Snapshot_pb2.py
hbase/protobuf/Tracing_pb2.py
hbase/protobuf/VisibilityLabels_pb2.py
hbase/protobuf/WAL_pb2.py
hbase/protobuf/ZooKeeper_pb2.py
hbase/protobuf/__init__.py
hbase/services/__init__.py
hbase/services/request.py
hbase/services/services.py
hbase/services/zookeeper.py
hbase_python-0.5.dist-info/DESCRIPTION.rst
hbase_python-0.5.dist-info/METADATA
hbase_python-0.5.dist-info/RECORD
hbase_python-0.5.dist-info/WHEEL
hbase_python-0.5.dist-info/metadata.json
hbase_python-0.5.dist-info/top_level.txt
hbase_python-0.5.dist-info/zip-safe
