Metadata-Version: 2.0
Name: hbase-python
Version: 0.5
Summary: User friendly HBase client for Python 3. (Pure python implementation)
Home-page: https://github.com/3601314/hbase-python
Author: dm.ustc.edu.cn
Author-email: gylv@mail.ustc.edu.cn
License: Free
Keywords: hbase,hbase-client,hadoop
Platform: any
Classifier: Programming Language :: Python :: 3.4
Classifier: Programming Language :: Python :: 3.5
Classifier: Programming Language :: Python :: 3.6
Requires-Dist: requests
